elx/__init__.py
elx/catalog.py
elx/cli/__init__.py
elx/cli/app.py
elx/cli/catalog.py
elx/cli/debug.py
elx/cli/invoke.py
elx/cli/utils.py
elx/exceptions.py
elx/extensions/__init__.py
elx/extensions/dagster/__init__.py
elx/extensions/dagster/assets.py
elx/extensions/dagster/utils.py
elx/json_temp_file.py
elx/runner.py
elx/singer.py
elx/state.py
elx/tap.py
elx/target.py
elx/utils.py
elx-0.2.2.dist-info/METADATA
elx-0.2.2.dist-info/WHEEL
elx-0.2.2.dist-info/entry_points.txt
elx-0.2.2.dist-info/RECORD
