Metadata-Version: 2.3
Name: elx
Version: 0.2.2
Summary: A lightweight Python interface for extracting and loading using the Singer.io spec.
Author: Jules Huisman
Author-email: jules.huisman@quantile.nl
Requires-Python: >=3.10,<4.0
Classifier: Programming Language :: Python :: 3
Classifier: Programming Language :: Python :: 3.10
Classifier: Programming Language :: Python :: 3.11
Classifier: Programming Language :: Python :: 3.12
Classifier: Programming Language :: Python :: 3.13
Provides-Extra: all
Provides-Extra: aws
Provides-Extra: azure
Provides-Extra: dagster
Provides-Extra: gcs
Provides-Extra: http
Provides-Extra: ssh
Requires-Dist: azure-common (>=1.0.0,<2.0.0) ; extra == "azure" or extra == "all"
Requires-Dist: azure-core (>=1.0.0,<2.0.0) ; extra == "azure" or extra == "all"
Requires-Dist: azure-storage-blob (>=12.0.0,<13.0.0) ; extra == "azure" or extra == "all"
Requires-Dist: boto3 (>=1.0.0,<2.0.0) ; extra == "aws" or extra == "all"
Requires-Dist: dagster (>=1.5.6,<2.0.0) ; extra == "dagster" or extra == "all"
Requires-Dist: dagster-webserver (>=1.5.6,<2.0.0) ; extra == "dagster"
Requires-Dist: google-cloud-storage (>=2.6.0,<3.0.0) ; extra == "gcs" or extra == "all"
Requires-Dist: inquirer (>=3.1.3,<4.0.0)
Requires-Dist: paramiko (>=2.0.0,<3.0.0) ; extra == "ssh" or extra == "all"
Requires-Dist: pipx (>=1.2.0,<2.0.0)
Requires-Dist: pydantic (>=2.9,<3.0)
Requires-Dist: python-dotenv (>=1.0.0,<2.0.0)
Requires-Dist: requests (>=2.0.0,<3.0.0) ; extra == "http" or extra == "all"
Requires-Dist: smart-open (>=6.3.0,<7.0.0)
Requires-Dist: typer[all] (>=0.9.0,<0.10.0)
